README.md
setup.py
src/utk/__init__.py
src/utk/buildings.py
src/utk/cache.py
src/utk/data.py
src/utk/errors.py
src/utk/files_interface.py
src/utk/lineclipping.py
src/utk/load_physical.py
src/utk/load_thematic.py
src/utk/load_utk.py
src/utk/map.py
src/utk/osm.py
src/utk/shadow_accumulator.py
src/utk/urban_component.py
src/utk/utils.py
src/utk/utk.py
src/utk/../utk_server.py
src/utk/../../requirements.txt
src/utk/../utk-frontend/build/utk-app/27.be6b7ff5.chunk.js
src/utk/../utk-frontend/build/utk-app/android-chrome-192x192.png
src/utk/../utk-frontend/build/utk-app/android-chrome-512x512.png
src/utk/../utk-frontend/build/utk-app/apple-touch-icon.png
src/utk/../utk-frontend/build/utk-app/asset-manifest.json
src/utk/../utk-frontend/build/utk-app/favicon.ico
src/utk/../utk-frontend/build/utk-app/index.html
src/utk/../utk-frontend/build/utk-app/logo192.png
src/utk/../utk-frontend/build/utk-app/logo512.png
src/utk/../utk-frontend/build/utk-app/main.60ad8a0a.css
src/utk/../utk-frontend/build/utk-app/main.js
src/utk/../utk-frontend/build/utk-app/main.js.LICENSE.txt
src/utk/../utk-frontend/build/utk-app/manifest.json
src/utk/../utk-frontend/build/utk-app/robots.txt
utk.egg-info/PKG-INFO
utk.egg-info/SOURCES.txt
utk.egg-info/dependency_links.txt
utk.egg-info/entry_points.txt
utk.egg-info/requires.txt
utk.egg-info/top_level.txt