Metadata-Version: 2.1
Name: utk
Version: 1.0.0
Summary: The Urban Toolkit: A Grammar-based Framework for Urban Visual Analytics
Home-page: https://github.com/urban-toolkit/urbantk/tree/main/
Author: Fabio Miranda
Author-email: fabiom@uic.edu
Requires-Python: >=3.8
